axp209.py
axp209-0.1.dist-info/LICENSE
axp209-0.1.dist-info/METADATA
axp209-0.1.dist-info/WHEEL
axp209-0.1.dist-info/entry_points.txt
axp209-0.1.dist-info/top_level.txt
axp209-0.1.dist-info/RECORD
