Metadata-Version: 2.1
Name: axp209
Version: 0.1
Summary: axp209 is a pure python library for getting information from AXP209 Power Management Unit
Home-page: https://github.com/artizirk/python-axp209
Author: Arti Zirk
Author-email: arti.zirk@gmail.com
License: MIT
Keywords: sunxi,cubietruck,cubieboard,axp209,python,i2c,CHIP,linux,allwinner
Platform: UNKNOWN
Classifier: Development Status :: 3 - Alpha
Classifier: Topic :: Utilities
Classifier: License :: OSI Approved :: MIT License
Classifier: Programming Language :: Python :: 2
Classifier: Programming Language :: Python :: 2.7
Classifier: Programming Language :: Python :: 3
Classifier: Programming Language :: Python :: 3.4
Classifier: Programming Language :: Python :: 3.5
Requires-Dist: smbus2 (>=0.1.3)
